setup.py
gflags_multibool/__init__.py
gflags_multibool/gflags_multibool_test.py
gflags_multibool.egg-info/PKG-INFO
gflags_multibool.egg-info/SOURCES.txt
gflags_multibool.egg-info/dependency_links.txt
gflags_multibool.egg-info/requires.txt
gflags_multibool.egg-info/top_level.txt
gflags_multibool.egg-info/zip-safe