Metadata-Version: 1.0
Name: gflags-multibool
Version: 0.0.0
Summary: GFlags multibool
Home-page: UNKNOWN
Author: Adam DePrince
Author-email: adeprince@googlealumni.com
License: UNKNOWN
Platform: UNKNOWN
